[
  {
    "id": 1,
    "name": "병용금기 - 이트라코나졸 + 심바스타틴",
    "method": "graph-rag",
    "elapsed": 3593,
    "detectedCount": 4,
    "expectedCount": 1,
    "detected": [
      {
        "type": "CONTRAINDICATED",
        "involvedIngredients": [
          "심바스타틴",
          "이트라코나졸"
        ]
      },
      {
        "type": "CONTRAINDICATED",
        "involvedIngredients": [
          "심바스타틴",
          "이트라코나졸"
        ]
      },
      {
        "type": "PREGNANCY",
        "involvedIngredients": [
          "이트라코나졸"
        ]
      },
      {
        "type": "PREGNANCY",
        "involvedIngredients": [
          "심바스타틴"
        ]
      }
    ],
    "expected": [
      {
        "type": "CONTRAINDICATED",
        "involvedIngredients": [
          "이트라코나졸",
          "심바스타틴"
        ]
      }
    ],
    "recall": 1
  },
  {
    "id": 2,
    "name": "병용금기 - 메트포르민 + 이오딕사놀",
    "method": "graph-rag",
    "elapsed": 2958,
    "detectedCount": 4,
    "expectedCount": 1,
    "detected": [
      {
        "type": "CONTRAINDICATED",
        "involvedIngredients": [
          "메트포르민",
          "이오딕사놀"
        ]
      },
      {
        "type": "CONTRAINDICATED",
        "involvedIngredients": [
          "메트포르민",
          "이오딕사놀"
        ]
      },
      {
        "type": "PREGNANCY",
        "involvedIngredients": [
          "이오딕사놀"
        ]
      },
      {
        "type": "PREGNANCY",
        "involvedIngredients": [
          "메트포르민"
        ]
      }
    ],
    "expected": [
      {
        "type": "CONTRAINDICATED",
        "involvedIngredients": [
          "메트포르민",
          "이오딕사놀"
        ]
      }
    ],
    "recall": 1
  },
  {
    "id": 3,
    "name": "병용금기 - 메트포르민 + 이오트로란",
    "method": "graph-rag",
    "elapsed": 2238,
    "detectedCount": 3,
    "expectedCount": 1,
    "detected": [
      {
        "type": "CONTRAINDICATED",
        "involvedIngredients": [
          "메트포르민",
          "이오트로란"
        ]
      },
      {
        "type": "CONTRAINDICATED",
        "involvedIngredients": [
          "메트포르민",
          "이오트로란"
        ]
      },
      {
        "type": "PREGNANCY",
        "involvedIngredients": [
          "메트포르민"
        ]
      }
    ],
    "expected": [
      {
        "type": "CONTRAINDICATED",
        "involvedIngredients": [
          "메트포르민",
          "이오트로란"
        ]
      }
    ],
    "recall": 1
  },
  {
    "id": 4,
    "name": "병용금기 - 메토트렉세이트 + 티아프로펜산",
    "method": "graph-rag",
    "elapsed": 2732,
    "detectedCount": 4,
    "expectedCount": 1,
    "detected": [
      {
        "type": "CONTRAINDICATED",
        "involvedIngredients": [
          "메토트렉세이트",
          "티아프로펜산"
        ]
      },
      {
        "type": "ELDERLY",
        "involvedIngredients": [
          "티아프로펜산"
        ]
      },
      {
        "type": "PREGNANCY",
        "involvedIngredients": [
          "티아프로펜산"
        ]
      },
      {
        "type": "PREGNANCY",
        "involvedIngredients": [
          "메토트렉세이트"
        ]
      }
    ],
    "expected": [
      {
        "type": "CONTRAINDICATED",
        "involvedIngredients": [
          "메토트렉세이트",
          "티아프로펜산"
        ]
      }
    ],
    "recall": 1
  },
  {
    "id": 5,
    "name": "병용금기 - 포르모테롤 + 노르에피네프린",
    "method": "graph-rag",
    "elapsed": 3626,
    "detectedCount": 3,
    "expectedCount": 1,
    "detected": [
      {
        "type": "CONTRAINDICATED",
        "involvedIngredients": [
          "노르에피네프린",
          "포르모테롤"
        ]
      },
      {
        "type": "PREGNANCY",
        "involvedIngredients": [
          "포르모테롤"
        ]
      },
      {
        "type": "PREGNANCY",
        "involvedIngredients": [
          "노르에피네프린"
        ]
      }
    ],
    "expected": [
      {
        "type": "CONTRAINDICATED",
        "involvedIngredients": [
          "포르모테롤",
          "노르에피네프린"
        ]
      }
    ],
    "recall": 1
  },
  {
    "id": 6,
    "name": "병용금기 - 포르모테롤 + 에피네프린",
    "method": "graph-rag",
    "elapsed": 2792,
    "detectedCount": 3,
    "expectedCount": 1,
    "detected": [
      {
        "type": "CONTRAINDICATED",
        "involvedIngredients": [
          "에피네프린",
          "포르모테롤"
        ]
      },
      {
        "type": "PREGNANCY",
        "involvedIngredients": [
          "포르모테롤"
        ]
      },
      {
        "type": "PREGNANCY",
        "involvedIngredients": [
          "에피네프린"
        ]
      }
    ],
    "expected": [
      {
        "type": "CONTRAINDICATED",
        "involvedIngredients": [
          "포르모테롤",
          "에피네프린"
        ]
      }
    ],
    "recall": 1
  },
  {
    "id": 7,
    "name": "병용금기 - 덱사메타손 + 스파플록사신",
    "method": "graph-rag",
    "elapsed": 2471,
    "detectedCount": 3,
    "expectedCount": 1,
    "detected": [
      {
        "type": "CONTRAINDICATED",
        "involvedIngredients": [
          "덱사메타손",
          "스파플록사신"
        ]
      },
      {
        "type": "PREGNANCY",
        "involvedIngredients": [
          "덱사메타손"
        ]
      },
      {
        "type": "PREGNANCY",
        "involvedIngredients": [
          "스파플록사신"
        ]
      }
    ],
    "expected": [
      {
        "type": "CONTRAINDICATED",
        "involvedIngredients": [
          "덱사메타손",
          "스파플록사신"
        ]
      }
    ],
    "recall": 1
  },
  {
    "id": 8,
    "name": "병용금기 - 히드로코르티손 + 스파플록사신",
    "method": "graph-rag",
    "elapsed": 2944,
    "detectedCount": 3,
    "expectedCount": 1,
    "detected": [
      {
        "type": "CONTRAINDICATED",
        "involvedIngredients": [
          "스파플록사신",
          "히드로코르티손"
        ]
      },
      {
        "type": "PREGNANCY",
        "involvedIngredients": [
          "히드로코르티손"
        ]
      },
      {
        "type": "PREGNANCY",
        "involvedIngredients": [
          "스파플록사신"
        ]
      }
    ],
    "expected": [
      {
        "type": "CONTRAINDICATED",
        "involvedIngredients": [
          "히드로코르티손",
          "스파플록사신"
        ]
      }
    ],
    "recall": 1
  },
  {
    "id": 9,
    "name": "병용금기 - 프레드니솔론 + 스파플록사신",
    "method": "graph-rag",
    "elapsed": 2596,
    "detectedCount": 3,
    "expectedCount": 1,
    "detected": [
      {
        "type": "CONTRAINDICATED",
        "involvedIngredients": [
          "스파플록사신",
          "프레드니솔론"
        ]
      },
      {
        "type": "PREGNANCY",
        "involvedIngredients": [
          "프레드니솔론"
        ]
      },
      {
        "type": "PREGNANCY",
        "involvedIngredients": [
          "스파플록사신"
        ]
      }
    ],
    "expected": [
      {
        "type": "CONTRAINDICATED",
        "involvedIngredients": [
          "프레드니솔론",
          "스파플록사신"
        ]
      }
    ],
    "recall": 1
  },
  {
    "id": 10,
    "name": "병용금기 - 헥소프레날린 + 노르에피네프린",
    "method": "graph-rag",
    "elapsed": 3074,
    "detectedCount": 2,
    "expectedCount": 1,
    "detected": [
      {
        "type": "CONTRAINDICATED",
        "involvedIngredients": [
          "노르에피네프린",
          "헥소프레날린"
        ]
      },
      {
        "type": "PREGNANCY",
        "involvedIngredients": [
          "노르에피네프린"
        ]
      }
    ],
    "expected": [
      {
        "type": "CONTRAINDICATED",
        "involvedIngredients": [
          "헥소프레날린",
          "노르에피네프린"
        ]
      }
    ],
    "recall": 1
  },
  {
    "id": 11,
    "name": "노인주의 - 플루라제팜",
    "method": "graph-rag",
    "elapsed": 2307,
    "detectedCount": 2,
    "expectedCount": 1,
    "detected": [
      {
        "type": "ELDERLY",
        "involvedIngredients": [
          "플루라제팜"
        ]
      },
      {
        "type": "PREGNANCY",
        "involvedIngredients": [
          "플루라제팜"
        ]
      }
    ],
    "expected": [
      {
        "type": "ELDERLY",
        "involvedIngredients": [
          "플루라제팜"
        ]
      }
    ],
    "recall": 1
  },
  {
    "id": 12,
    "name": "노인주의 - 디아제팜",
    "method": "graph-rag",
    "elapsed": 2545,
    "detectedCount": 2,
    "expectedCount": 1,
    "detected": [
      {
        "type": "ELDERLY",
        "involvedIngredients": [
          "디아제팜"
        ]
      },
      {
        "type": "PREGNANCY",
        "involvedIngredients": [
          "디아제팜"
        ]
      }
    ],
    "expected": [
      {
        "type": "ELDERLY",
        "involvedIngredients": [
          "디아제팜"
        ]
      }
    ],
    "recall": 1
  },
  {
    "id": 13,
    "name": "노인주의 - 클로르디아제폭시드",
    "method": "graph-rag",
    "elapsed": 2768,
    "detectedCount": 2,
    "expectedCount": 1,
    "detected": [
      {
        "type": "ELDERLY",
        "involvedIngredients": [
          "클로르디아제폭시드"
        ]
      },
      {
        "type": "PREGNANCY",
        "involvedIngredients": [
          "클로르디아제폭시드"
        ]
      }
    ],
    "expected": [
      {
        "type": "ELDERLY",
        "involvedIngredients": [
          "클로르디아제폭시드"
        ]
      }
    ],
    "recall": 1
  },
  {
    "id": 14,
    "name": "노인주의 - 클로나제팜",
    "method": "graph-rag",
    "elapsed": 2354,
    "detectedCount": 2,
    "expectedCount": 1,
    "detected": [
      {
        "type": "ELDERLY",
        "involvedIngredients": [
          "클로나제팜"
        ]
      },
      {
        "type": "PREGNANCY",
        "involvedIngredients": [
          "클로나제팜"
        ]
      }
    ],
    "expected": [
      {
        "type": "ELDERLY",
        "involvedIngredients": [
          "클로나제팜"
        ]
      }
    ],
    "recall": 1
  },
  {
    "id": 15,
    "name": "노인주의 - 몰린돈",
    "method": "graph-rag",
    "elapsed": 2090,
    "detectedCount": 2,
    "expectedCount": 1,
    "detected": [
      {
        "type": "ELDERLY",
        "involvedIngredients": [
          "몰린돈"
        ]
      },
      {
        "type": "PREGNANCY",
        "involvedIngredients": [
          "몰린돈"
        ]
      }
    ],
    "expected": [
      {
        "type": "ELDERLY",
        "involvedIngredients": [
          "몰린돈"
        ]
      }
    ],
    "recall": 1
  },
  {
    "id": 16,
    "name": "노인주의 - 플루니트라제팜",
    "method": "graph-rag",
    "elapsed": 1598,
    "detectedCount": 2,
    "expectedCount": 1,
    "detected": [
      {
        "type": "ELDERLY",
        "involvedIngredients": [
          "플루니트라제팜"
        ]
      },
      {
        "type": "PREGNANCY",
        "involvedIngredients": [
          "플루니트라제팜"
        ]
      }
    ],
    "expected": [
      {
        "type": "ELDERLY",
        "involvedIngredients": [
          "플루니트라제팜"
        ]
      }
    ],
    "recall": 1
  },
  {
    "id": 17,
    "name": "노인주의 - 클로바잠",
    "method": "graph-rag",
    "elapsed": 2081,
    "detectedCount": 2,
    "expectedCount": 1,
    "detected": [
      {
        "type": "ELDERLY",
        "involvedIngredients": [
          "클로바잠"
        ]
      },
      {
        "type": "PREGNANCY",
        "involvedIngredients": [
          "클로바잠"
        ]
      }
    ],
    "expected": [
      {
        "type": "ELDERLY",
        "involvedIngredients": [
          "클로바잠"
        ]
      }
    ],
    "recall": 1
  },
  {
    "id": 18,
    "name": "노인주의 - 멕사졸람",
    "method": "graph-rag",
    "elapsed": 2146,
    "detectedCount": 2,
    "expectedCount": 1,
    "detected": [
      {
        "type": "ELDERLY",
        "involvedIngredients": [
          "멕사졸람"
        ]
      },
      {
        "type": "PREGNANCY",
        "involvedIngredients": [
          "멕사졸람"
        ]
      }
    ],
    "expected": [
      {
        "type": "ELDERLY",
        "involvedIngredients": [
          "멕사졸람"
        ]
      }
    ],
    "recall": 1
  },
  {
    "id": 19,
    "name": "효능군중복 - 아스피린 + 이부프로펜 (소염제)",
    "method": "graph-rag",
    "elapsed": 5409,
    "detectedCount": 5,
    "expectedCount": 1,
    "detected": [
      {
        "type": "ELDERLY",
        "involvedIngredients": [
          "아스피린"
        ]
      },
      {
        "type": "ELDERLY",
        "involvedIngredients": [
          "이부프로펜"
        ]
      },
      {
        "type": "DUPLICATE",
        "involvedIngredients": [
          "아스피린",
          "이부프로펜"
        ]
      },
      {
        "type": "PREGNANCY",
        "involvedIngredients": [
          "아스피린"
        ]
      },
      {
        "type": "PREGNANCY",
        "involvedIngredients": [
          "이부프로펜"
        ]
      }
    ],
    "expected": [
      {
        "type": "DUPLICATE",
        "involvedIngredients": [
          "아스피린",
          "이부프로펜"
        ]
      }
    ],
    "recall": 1
  },
  {
    "id": 20,
    "name": "효능군중복 - 아세클로페낙 + 나프록센 (소염제)",
    "method": "graph-rag",
    "elapsed": 4680,
    "detectedCount": 5,
    "expectedCount": 1,
    "detected": [
      {
        "type": "ELDERLY",
        "involvedIngredients": [
          "나프록센"
        ]
      },
      {
        "type": "ELDERLY",
        "involvedIngredients": [
          "아세클로페낙"
        ]
      },
      {
        "type": "DUPLICATE",
        "involvedIngredients": [
          "나프록센",
          "아세클로페낙"
        ]
      },
      {
        "type": "PREGNANCY",
        "involvedIngredients": [
          "나프록센"
        ]
      },
      {
        "type": "PREGNANCY",
        "involvedIngredients": [
          "아세클로페낙"
        ]
      }
    ],
    "expected": [
      {
        "type": "DUPLICATE",
        "involvedIngredients": [
          "아세클로페낙",
          "나프록센"
        ]
      }
    ],
    "recall": 1
  },
  {
    "id": 21,
    "name": "효능군중복 - 세레콕시브 + 디클로페낙 (소염제)",
    "method": "graph-rag",
    "elapsed": 5095,
    "detectedCount": 5,
    "expectedCount": 1,
    "detected": [
      {
        "type": "ELDERLY",
        "involvedIngredients": [
          "세레콕시브"
        ]
      },
      {
        "type": "ELDERLY",
        "involvedIngredients": [
          "디클로페낙"
        ]
      },
      {
        "type": "DUPLICATE",
        "involvedIngredients": [
          "세레콕시브",
          "디클로페낙"
        ]
      },
      {
        "type": "PREGNANCY",
        "involvedIngredients": [
          "세레콕시브"
        ]
      },
      {
        "type": "PREGNANCY",
        "involvedIngredients": [
          "디클로페낙"
        ]
      }
    ],
    "expected": [
      {
        "type": "DUPLICATE",
        "involvedIngredients": [
          "세레콕시브",
          "디클로페낙"
        ]
      }
    ],
    "recall": 1
  },
  {
    "id": 22,
    "name": "효능군중복 - 포르모테롤 + 살부타몰 (베타수용체)",
    "method": "graph-rag",
    "elapsed": 3074,
    "detectedCount": 3,
    "expectedCount": 1,
    "detected": [
      {
        "type": "DUPLICATE",
        "involvedIngredients": [
          "포르모테롤",
          "살부타몰"
        ]
      },
      {
        "type": "PREGNANCY",
        "involvedIngredients": [
          "포르모테롤"
        ]
      },
      {
        "type": "PREGNANCY",
        "involvedIngredients": [
          "살부타몰"
        ]
      }
    ],
    "expected": [
      {
        "type": "DUPLICATE",
        "involvedIngredients": [
          "포르모테롤",
          "살부타몰"
        ]
      }
    ],
    "recall": 1
  },
  {
    "id": 23,
    "name": "효능군중복 - 팔리페리돈 + 리스페리돈 (항정신병)",
    "method": "graph-rag",
    "elapsed": 4163,
    "detectedCount": 5,
    "expectedCount": 1,
    "detected": [
      {
        "type": "ELDERLY",
        "involvedIngredients": [
          "팔리페리돈"
        ]
      },
      {
        "type": "ELDERLY",
        "involvedIngredients": [
          "리스페리돈"
        ]
      },
      {
        "type": "DUPLICATE",
        "involvedIngredients": [
          "팔리페리돈",
          "리스페리돈"
        ]
      },
      {
        "type": "PREGNANCY",
        "involvedIngredients": [
          "팔리페리돈"
        ]
      },
      {
        "type": "PREGNANCY",
        "involvedIngredients": [
          "리스페리돈"
        ]
      }
    ],
    "expected": [
      {
        "type": "DUPLICATE",
        "involvedIngredients": [
          "팔리페리돈",
          "리스페리돈"
        ]
      }
    ],
    "recall": 1
  },
  {
    "id": 24,
    "name": "효능군중복 - 쿠에티아핀 + 올란자핀 (항정신병)",
    "method": "graph-rag",
    "elapsed": 6508,
    "detectedCount": 5,
    "expectedCount": 1,
    "detected": [
      {
        "type": "ELDERLY",
        "involvedIngredients": [
          "쿠에티아핀"
        ]
      },
      {
        "type": "ELDERLY",
        "involvedIngredients": [
          "올란자핀"
        ]
      },
      {
        "type": "DUPLICATE",
        "involvedIngredients": [
          "쿠에티아핀",
          "올란자핀"
        ]
      },
      {
        "type": "PREGNANCY",
        "involvedIngredients": [
          "쿠에티아핀"
        ]
      },
      {
        "type": "PREGNANCY",
        "involvedIngredients": [
          "올란자핀"
        ]
      }
    ],
    "expected": [
      {
        "type": "DUPLICATE",
        "involvedIngredients": [
          "쿠에티아핀",
          "올란자핀"
        ]
      }
    ],
    "recall": 1
  },
  {
    "id": 25,
    "name": "효능군중복 - 글리메피리드 + 글리클라지드 (설포닐우레아)",
    "method": "graph-rag",
    "elapsed": 2637,
    "detectedCount": 3,
    "expectedCount": 1,
    "detected": [
      {
        "type": "DUPLICATE",
        "involvedIngredients": [
          "글리메피리드",
          "글리클라지드"
        ]
      },
      {
        "type": "PREGNANCY",
        "involvedIngredients": [
          "글리메피리드"
        ]
      },
      {
        "type": "PREGNANCY",
        "involvedIngredients": [
          "글리클라지드"
        ]
      }
    ],
    "expected": [
      {
        "type": "DUPLICATE",
        "involvedIngredients": [
          "글리메피리드",
          "글리클라지드"
        ]
      }
    ],
    "recall": 1
  },
  {
    "id": 26,
    "name": "효능군중복 - 베라파밀 + 딜티아젬 (CCB)",
    "method": "graph-rag",
    "elapsed": 4206,
    "detectedCount": 3,
    "expectedCount": 1,
    "detected": [
      {
        "type": "DUPLICATE",
        "involvedIngredients": [
          "베라파밀",
          "딜티아젬"
        ]
      },
      {
        "type": "PREGNANCY",
        "involvedIngredients": [
          "베라파밀"
        ]
      },
      {
        "type": "PREGNANCY",
        "involvedIngredients": [
          "딜티아젬"
        ]
      }
    ],
    "expected": [
      {
        "type": "DUPLICATE",
        "involvedIngredients": [
          "베라파밀",
          "딜티아젬"
        ]
      }
    ],
    "recall": 1
  },
  {
    "id": 27,
    "name": "임부금기 1등급 - 로수바스타틴",
    "method": "graph-rag",
    "elapsed": 1243,
    "detectedCount": 1,
    "expectedCount": 1,
    "detected": [
      {
        "type": "PREGNANCY",
        "involvedIngredients": [
          "로수바스타틴"
        ]
      }
    ],
    "expected": [
      {
        "type": "PREGNANCY",
        "involvedIngredients": [
          "로수바스타틴"
        ]
      }
    ],
    "recall": 1
  },
  {
    "id": 28,
    "name": "임부금기 1등급 - 프라바스타틴",
    "method": "graph-rag",
    "elapsed": 1179,
    "detectedCount": 1,
    "expectedCount": 1,
    "detected": [
      {
        "type": "PREGNANCY",
        "involvedIngredients": [
          "프라바스타틴"
        ]
      }
    ],
    "expected": [
      {
        "type": "PREGNANCY",
        "involvedIngredients": [
          "프라바스타틴"
        ]
      }
    ],
    "recall": 1
  },
  {
    "id": 29,
    "name": "임부금기 1등급 - 플루바스타틴",
    "method": "graph-rag",
    "elapsed": 1453,
    "detectedCount": 1,
    "expectedCount": 1,
    "detected": [
      {
        "type": "PREGNANCY",
        "involvedIngredients": [
          "플루바스타틴"
        ]
      }
    ],
    "expected": [
      {
        "type": "PREGNANCY",
        "involvedIngredients": [
          "플루바스타틴"
        ]
      }
    ],
    "recall": 1
  },
  {
    "id": 30,
    "name": "임부금기 1등급 - 피타바스타틴",
    "method": "graph-rag",
    "elapsed": 1253,
    "detectedCount": 1,
    "expectedCount": 1,
    "detected": [
      {
        "type": "PREGNANCY",
        "involvedIngredients": [
          "피타바스타틴"
        ]
      }
    ],
    "expected": [
      {
        "type": "PREGNANCY",
        "involvedIngredients": [
          "피타바스타틴"
        ]
      }
    ],
    "recall": 1
  },
  {
    "id": 31,
    "name": "임부금기 1등급 - 플루오로우라실",
    "method": "graph-rag",
    "elapsed": 1141,
    "detectedCount": 1,
    "expectedCount": 1,
    "detected": [
      {
        "type": "PREGNANCY",
        "involvedIngredients": [
          "플루오로우라실"
        ]
      }
    ],
    "expected": [
      {
        "type": "PREGNANCY",
        "involvedIngredients": [
          "플루오로우라실"
        ]
      }
    ],
    "recall": 1
  },
  {
    "id": 32,
    "name": "임부금기 1등급 - 에티닐에스트라디올",
    "method": "graph-rag",
    "elapsed": 2491,
    "detectedCount": 1,
    "expectedCount": 1,
    "detected": [
      {
        "type": "PREGNANCY",
        "involvedIngredients": [
          "에티닐에스트라디올"
        ]
      }
    ],
    "expected": [
      {
        "type": "PREGNANCY",
        "involvedIngredients": [
          "에티닐에스트라디올"
        ]
      }
    ],
    "recall": 1
  },
  {
    "id": 33,
    "name": "투여기간주의 - 나프록센 초과",
    "method": "graph-rag",
    "elapsed": 4609,
    "detectedCount": 3,
    "expectedCount": 1,
    "detected": [
      {
        "type": "ELDERLY",
        "involvedIngredients": [
          "나프록센"
        ]
      },
      {
        "type": "PREGNANCY",
        "involvedIngredients": [
          "나프록센"
        ]
      },
      {
        "type": "DURATION",
        "involvedIngredients": [
          "나프록센"
        ]
      }
    ],
    "expected": [
      {
        "type": "DURATION",
        "involvedIngredients": [
          "나프록센"
        ]
      }
    ],
    "recall": 1
  },
  {
    "id": 34,
    "name": "투여기간주의 - 졸피뎀 초과",
    "method": "graph-rag",
    "elapsed": 2645,
    "detectedCount": 2,
    "expectedCount": 1,
    "detected": [
      {
        "type": "PREGNANCY",
        "involvedIngredients": [
          "졸피뎀타르타르산염"
        ]
      },
      {
        "type": "DURATION",
        "involvedIngredients": [
          "졸피뎀타르타르산염"
        ]
      }
    ],
    "expected": [
      {
        "type": "DURATION",
        "involvedIngredients": [
          "졸피뎀타르타르산염"
        ]
      }
    ],
    "recall": 1
  },
  {
    "id": 35,
    "name": "투여기간주의 - 트리아졸람 초과",
    "method": "graph-rag",
    "elapsed": 2387,
    "detectedCount": 2,
    "expectedCount": 1,
    "detected": [
      {
        "type": "PREGNANCY",
        "involvedIngredients": [
          "트리아졸람"
        ]
      },
      {
        "type": "DURATION",
        "involvedIngredients": [
          "트리아졸람"
        ]
      }
    ],
    "expected": [
      {
        "type": "DURATION",
        "involvedIngredients": [
          "트리아졸람"
        ]
      }
    ],
    "recall": 1
  },
  {
    "id": 36,
    "name": "투여기간주의 - 리네졸리드 초과",
    "method": "graph-rag",
    "elapsed": 2640,
    "detectedCount": 2,
    "expectedCount": 1,
    "detected": [
      {
        "type": "PREGNANCY",
        "involvedIngredients": [
          "리네졸리드"
        ]
      },
      {
        "type": "DURATION",
        "involvedIngredients": [
          "리네졸리드"
        ]
      }
    ],
    "expected": [
      {
        "type": "DURATION",
        "involvedIngredients": [
          "리네졸리드"
        ]
      }
    ],
    "recall": 1
  },
  {
    "id": 37,
    "name": "투여기간주의 - 클로르페니라민 초과",
    "method": "graph-rag",
    "elapsed": 2190,
    "detectedCount": 2,
    "expectedCount": 1,
    "detected": [
      {
        "type": "ELDERLY",
        "involvedIngredients": [
          "클로르페니라민"
        ]
      },
      {
        "type": "DURATION",
        "involvedIngredients": [
          "클로르페니라민"
        ]
      }
    ],
    "expected": [
      {
        "type": "DURATION",
        "involvedIngredients": [
          "클로르페니라민"
        ]
      }
    ],
    "recall": 1
  },
  {
    "id": 38,
    "name": "투여기간주의 - 옥시메타졸린 초과",
    "method": "graph-rag",
    "elapsed": 5649,
    "detectedCount": 1,
    "expectedCount": 1,
    "detected": [
      {
        "type": "DURATION",
        "involvedIngredients": [
          "옥시메타졸린"
        ]
      }
    ],
    "expected": [
      {
        "type": "DURATION",
        "involvedIngredients": [
          "옥시메타졸린"
        ]
      }
    ],
    "recall": 1
  },
  {
    "id": 39,
    "name": "안전한 조합 - 비타민C + 오메가3",
    "method": "graph-rag",
    "elapsed": 18,
    "detectedCount": 0,
    "expectedCount": 0,
    "detected": [],
    "expected": [],
    "recall": 1
  },
  {
    "id": 40,
    "name": "안전한 조합 - 단일 성분 (아세트아미노펜)",
    "method": "graph-rag",
    "elapsed": 31,
    "detectedCount": 0,
    "expectedCount": 0,
    "detected": [],
    "expected": [],
    "recall": 1
  },
  {
    "id": 41,
    "name": "복합 - 병용금기 + 노인주의",
    "method": "graph-rag",
    "elapsed": 9969,
    "detectedCount": 4,
    "expectedCount": 2,
    "detected": [
      {
        "type": "ELDERLY",
        "involvedIngredients": [
          "플루라제팜"
        ]
      },
      {
        "type": "ELDERLY",
        "involvedIngredients": [
          "디아제팜"
        ]
      },
      {
        "type": "PREGNANCY",
        "involvedIngredients": [
          "플루라제팜"
        ]
      },
      {
        "type": "PREGNANCY",
        "involvedIngredients": [
          "디아제팜"
        ]
      }
    ],
    "expected": [
      {
        "type": "ELDERLY",
        "involvedIngredients": [
          "디아제팜"
        ]
      },
      {
        "type": "ELDERLY",
        "involvedIngredients": [
          "플루라제팜"
        ]
      }
    ],
    "recall": 1
  },
  {
    "id": 42,
    "name": "복합 - 효능군중복 + 노인주의",
    "method": "graph-rag",
    "elapsed": 3481,
    "detectedCount": 5,
    "expectedCount": 3,
    "detected": [
      {
        "type": "ELDERLY",
        "involvedIngredients": [
          "이부프로펜"
        ]
      },
      {
        "type": "ELDERLY",
        "involvedIngredients": [
          "아세클로페낙"
        ]
      },
      {
        "type": "DUPLICATE",
        "involvedIngredients": [
          "이부프로펜",
          "아세클로페낙"
        ]
      },
      {
        "type": "PREGNANCY",
        "involvedIngredients": [
          "이부프로펜"
        ]
      },
      {
        "type": "PREGNANCY",
        "involvedIngredients": [
          "아세클로페낙"
        ]
      }
    ],
    "expected": [
      {
        "type": "DUPLICATE",
        "involvedIngredients": [
          "아세클로페낙",
          "이부프로펜"
        ]
      },
      {
        "type": "ELDERLY",
        "involvedIngredients": [
          "아세클로페낙"
        ]
      },
      {
        "type": "ELDERLY",
        "involvedIngredients": [
          "이부프로펜"
        ]
      }
    ],
    "recall": 1
  },
  {
    "id": 43,
    "name": "복합 - 병용금기 + 효능군중복",
    "method": "graph-rag",
    "elapsed": 3177,
    "detectedCount": 6,
    "expectedCount": 2,
    "detected": [
      {
        "type": "CONTRAINDICATED",
        "involvedIngredients": [
          "메트포르민",
          "이오트로란"
        ]
      },
      {
        "type": "CONTRAINDICATED",
        "involvedIngredients": [
          "메트포르민",
          "이오딕사놀"
        ]
      },
      {
        "type": "CONTRAINDICATED",
        "involvedIngredients": [
          "메트포르민",
          "이오트로란"
        ]
      },
      {
        "type": "CONTRAINDICATED",
        "involvedIngredients": [
          "메트포르민",
          "이오딕사놀"
        ]
      },
      {
        "type": "PREGNANCY",
        "involvedIngredients": [
          "이오딕사놀"
        ]
      },
      {
        "type": "PREGNANCY",
        "involvedIngredients": [
          "메트포르민"
        ]
      }
    ],
    "expected": [
      {
        "type": "CONTRAINDICATED",
        "involvedIngredients": [
          "메트포르민",
          "이오딕사놀"
        ]
      },
      {
        "type": "CONTRAINDICATED",
        "involvedIngredients": [
          "메트포르민",
          "이오트로란"
        ]
      }
    ],
    "recall": 1
  },
  {
    "id": 44,
    "name": "복합 - 임부금기 + 병용금기",
    "method": "graph-rag",
    "elapsed": 4345,
    "detectedCount": 6,
    "expectedCount": 2,
    "detected": [
      {
        "type": "CONTRAINDICATED",
        "involvedIngredients": [
          "심바스타틴",
          "이트라코나졸"
        ]
      },
      {
        "type": "CONTRAINDICATED",
        "involvedIngredients": [
          "심바스타틴",
          "이트라코나졸"
        ]
      },
      {
        "type": "DUPLICATE",
        "involvedIngredients": [
          "로수바스타틴",
          "심바스타틴"
        ]
      },
      {
        "type": "PREGNANCY",
        "involvedIngredients": [
          "로수바스타틴"
        ]
      },
      {
        "type": "PREGNANCY",
        "involvedIngredients": [
          "이트라코나졸"
        ]
      },
      {
        "type": "PREGNANCY",
        "involvedIngredients": [
          "심바스타틴"
        ]
      }
    ],
    "expected": [
      {
        "type": "CONTRAINDICATED",
        "involvedIngredients": [
          "이트라코나졸",
          "심바스타틴"
        ]
      },
      {
        "type": "PREGNANCY",
        "involvedIngredients": [
          "로수바스타틴"
        ]
      }
    ],
    "recall": 1
  },
  {
    "id": 45,
    "name": "복합 - 다약제 (5개)",
    "method": "graph-rag",
    "elapsed": 6419,
    "detectedCount": 11,
    "expectedCount": 3,
    "detected": [
      {
        "type": "CONTRAINDICATED",
        "involvedIngredients": [
          "메트포르민",
          "이오딕사놀"
        ]
      },
      {
        "type": "CONTRAINDICATED",
        "involvedIngredients": [
          "메트포르민",
          "이오딕사놀"
        ]
      },
      {
        "type": "ELDERLY",
        "involvedIngredients": [
          "디아제팜"
        ]
      },
      {
        "type": "ELDERLY",
        "involvedIngredients": [
          "아스피린"
        ]
      },
      {
        "type": "ELDERLY",
        "involvedIngredients": [
          "이부프로펜"
        ]
      },
      {
        "type": "DUPLICATE",
        "involvedIngredients": [
          "아스피린",
          "이부프로펜"
        ]
      },
      {
        "type": "PREGNANCY",
        "involvedIngredients": [
          "이오딕사놀"
        ]
      },
      {
        "type": "PREGNANCY",
        "involvedIngredients": [
          "디아제팜"
        ]
      },
      {
        "type": "PREGNANCY",
        "involvedIngredients": [
          "아스피린"
        ]
      },
      {
        "type": "PREGNANCY",
        "involvedIngredients": [
          "이부프로펜"
        ]
      },
      {
        "type": "PREGNANCY",
        "involvedIngredients": [
          "메트포르민"
        ]
      }
    ],
    "expected": [
      {
        "type": "CONTRAINDICATED",
        "involvedIngredients": [
          "메트포르민",
          "이오딕사놀"
        ]
      },
      {
        "type": "DUPLICATE",
        "involvedIngredients": [
          "아스피린",
          "이부프로펜"
        ]
      },
      {
        "type": "ELDERLY",
        "involvedIngredients": [
          "디아제팜"
        ]
      }
    ],
    "recall": 1
  },
  {
    "id": 46,
    "name": "투여기간주의 - 기간 안 넘은 경우 (정상)",
    "method": "graph-rag",
    "elapsed": 2861,
    "detectedCount": 2,
    "expectedCount": 0,
    "detected": [
      {
        "type": "ELDERLY",
        "involvedIngredients": [
          "나프록센"
        ]
      },
      {
        "type": "PREGNANCY",
        "involvedIngredients": [
          "나프록센"
        ]
      }
    ],
    "expected": [],
    "recall": 0
  },
  {
    "id": 47,
    "name": "투여기간주의 - 딱 맞는 경우 (정상)",
    "method": "graph-rag",
    "elapsed": 1517,
    "detectedCount": 1,
    "expectedCount": 0,
    "detected": [
      {
        "type": "PREGNANCY",
        "involvedIngredients": [
          "트리아졸람"
        ]
      }
    ],
    "expected": [],
    "recall": 0
  },
  {
    "id": 48,
    "name": "노인주의 - 피나제팜",
    "method": "graph-rag",
    "elapsed": 2046,
    "detectedCount": 2,
    "expectedCount": 1,
    "detected": [
      {
        "type": "ELDERLY",
        "involvedIngredients": [
          "피나제팜"
        ]
      },
      {
        "type": "PREGNANCY",
        "involvedIngredients": [
          "피나제팜"
        ]
      }
    ],
    "expected": [
      {
        "type": "ELDERLY",
        "involvedIngredients": [
          "피나제팜"
        ]
      }
    ],
    "recall": 1
  },
  {
    "id": 49,
    "name": "효능군중복 - 독사조신 + 프라조신 (Alpha Blockers)",
    "method": "graph-rag",
    "elapsed": 1782,
    "detectedCount": 2,
    "expectedCount": 1,
    "detected": [
      {
        "type": "DUPLICATE",
        "involvedIngredients": [
          "독사조신",
          "프라조신"
        ]
      },
      {
        "type": "PREGNANCY",
        "involvedIngredients": [
          "독사조신"
        ]
      }
    ],
    "expected": [
      {
        "type": "DUPLICATE",
        "involvedIngredients": [
          "독사조신",
          "프라조신"
        ]
      }
    ],
    "recall": 1
  },
  {
    "id": 50,
    "name": "복합 - 노인주의 + 임부금기 + 투여기간주의",
    "method": "graph-rag",
    "elapsed": 3690,
    "detectedCount": 4,
    "expectedCount": 3,
    "detected": [
      {
        "type": "ELDERLY",
        "involvedIngredients": [
          "클로나제팜"
        ]
      },
      {
        "type": "PREGNANCY",
        "involvedIngredients": [
          "클로나제팜"
        ]
      },
      {
        "type": "PREGNANCY",
        "involvedIngredients": [
          "트리아졸람"
        ]
      },
      {
        "type": "DURATION",
        "involvedIngredients": [
          "트리아졸람"
        ]
      }
    ],
    "expected": [
      {
        "type": "ELDERLY",
        "involvedIngredients": [
          "클로나제팜"
        ]
      },
      {
        "type": "PREGNANCY",
        "involvedIngredients": [
          "트리아졸람"
        ]
      },
      {
        "type": "DURATION",
        "involvedIngredients": [
          "트리아졸람"
        ]
      }
    ],
    "recall": 1
  }
]